vcsver/__init__.py
vcsver/config.py
vcsver/errors.py
vcsver/git.py
vcsver/pep440.py
vcsver/setuptools.py
vcsver/setuptools_legacy.py
vcsver/types.py
vcsver/util.py
vcsver/vcsver.py
vcsver-0.2.dist-info/LICENSE.txt
vcsver-0.2.dist-info/METADATA
vcsver-0.2.dist-info/WHEEL
vcsver-0.2.dist-info/entry_points.txt
vcsver-0.2.dist-info/top_level.txt
vcsver-0.2.dist-info/RECORD
