Metadata-Version: 2.1
Name: vcsver
Version: 0.2
Summary: Automatic package version numbering from version control
Home-page: https://github.com/janneronkko/vcsver
Author: Janne Rönkkö
Author-email: janne.ronkko@iki.fi
License: MIT
Keywords: setuptools,development,git,version
Platform: UNKNOWN
Classifier: Development Status :: 3 - Alpha
Classifier: Intended Audience :: Developers
Classifier: License :: OSI Approved :: MIT License
Classifier: Operating System :: OS Independent
Classifier: Programming Language :: Python :: 3.7
Classifier: Programming Language :: Python :: 3.8
Classifier: Programming Language :: Python :: 3.9
Classifier: Programming Language :: Python :: 3.10
Classifier: Topic :: System :: Archiving :: Packaging
Requires-Python: >=3.7
License-File: LICENSE.txt
Requires-Dist: tomli
